djrill/__init__.py
djrill/_version.py
djrill/exceptions.py
djrill/forms.py
djrill/models.py
djrill/signals.py
djrill/urls.py
djrill/views.py
djrill/mail/__init__.py
djrill/mail/backends/__init__.py
djrill/mail/backends/djrill.py
djrill_fork-2.2.1.dist-info/licenses/AUTHORS.txt
djrill_fork-2.2.1.dist-info/licenses/LICENSE
djrill_fork-2.2.1.dist-info/METADATA
djrill_fork-2.2.1.dist-info/WHEEL
djrill_fork-2.2.1.dist-info/top_level.txt
djrill_fork-2.2.1.dist-info/RECORD
