Metadata-Version: 2.4
Name: djrill-fork
Version: 2.2.1
Summary: Mandrill transactional email for Django
Author-email: Kenneth Love <kenneth@brack3t.com>, Chris Jones <chris@brack3t.com>
Maintainer-email: Yupeek <devteam@yupeek.com>
License: Copyright (c) Brack3t and individual contributors.
Project-URL: source, https://github.com/Yupeek/Djrill/
Keywords: django,mailchimp,mandrill,email,email backend
Classifier: Programming Language :: Python
Classifier: Programming Language :: Python :: Implementation :: CPython
Classifier: Programming Language :: Python :: 3
Classifier: Programming Language :: Python :: 3 :: Only
Classifier: Programming Language :: Python :: 3.8
Classifier: Programming Language :: Python :: 3.9
Classifier: Programming Language :: Python :: 3.10
Classifier: Programming Language :: Python :: 3.11
Classifier: Programming Language :: Python :: 3.12
Classifier: Programming Language :: Python :: 3.13
Classifier: License :: OSI Approved :: BSD License
Classifier: Topic :: Software Development :: Libraries :: Python Modules
Classifier: Framework :: Django
Classifier: Framework :: Django :: 4
Classifier: Framework :: Django :: 4.0
Classifier: Framework :: Django :: 4.1
Classifier: Framework :: Django :: 4.2
Classifier: Framework :: Django :: 5
Classifier: Framework :: Django :: 5.0
Classifier: Framework :: Django :: 5.1
Classifier: Framework :: Django :: 5.2
Classifier: Environment :: Web Environment
Classifier: Development Status :: 5 - Production/Stable
Requires-Python: >=3.8
License-File: LICENSE
License-File: AUTHORS.txt
Requires-Dist: requests>=2.32
Requires-Dist: django>=4.0
Dynamic: description
Dynamic: description-content-type
Dynamic: license-file
